sphinx_tagtoctree/__init__.py
sphinx_tagtoctree-1.0.0.dist-info/AUTHORS
sphinx_tagtoctree-1.0.0.dist-info/LICENSE
sphinx_tagtoctree-1.0.0.dist-info/METADATA
sphinx_tagtoctree-1.0.0.dist-info/WHEEL
sphinx_tagtoctree-1.0.0.dist-info/pbr.json
sphinx_tagtoctree-1.0.0.dist-info/top_level.txt
sphinx_tagtoctree-1.0.0.dist-info/RECORD
